screen_ocr/__init__.py
screen_ocr/__main__.py
screen_ocr/_base.py
screen_ocr/_easyocr.py
screen_ocr/_screen_ocr.py
screen_ocr/_talon.py
screen_ocr/_tesseract.py
screen_ocr/_winrt.py
screen_ocr-0.7.0.dist-info/METADATA
screen_ocr-0.7.0.dist-info/WHEEL
screen_ocr-0.7.0.dist-info/licenses/LICENSE
screen_ocr-0.7.0.dist-info/RECORD
