Metadata-Version: 2.4
Name: screen-ocr
Version: 0.7.0
Summary: Library for processing screen contents using OCR
Project-URL: Homepage, https://github.com/wolfmanstout/screen-ocr
Author: James Stout
License-File: LICENSE
Classifier: License :: OSI Approved :: Apache Software License
Classifier: Operating System :: OS Independent
Classifier: Programming Language :: Python :: 3
Requires-Python: >=3.11
Requires-Dist: dxcam>=0.0.5; sys_platform == 'win32'
Requires-Dist: mss>=10.0.0; sys_platform == 'darwin'
Requires-Dist: pillow>=9.0
Requires-Dist: rapidfuzz
Provides-Extra: easyocr
Requires-Dist: easyocr; extra == 'easyocr'
Requires-Dist: numpy; extra == 'easyocr'
Provides-Extra: tesseract
Requires-Dist: numpy; extra == 'tesseract'
Requires-Dist: pandas; extra == 'tesseract'
Requires-Dist: pytesseract; extra == 'tesseract'
Requires-Dist: scikit-image; extra == 'tesseract'
Provides-Extra: winrt
Requires-Dist: winrt-windows-foundation-collections>=3.2.1; extra == 'winrt'
Requires-Dist: winrt-windows-foundation>=3.2.1; extra == 'winrt'
Requires-Dist: winrt-windows-graphics-imaging>=3.2.1; extra == 'winrt'
Requires-Dist: winrt-windows-media-ocr>=3.2.1; extra == 'winrt'
Requires-Dist: winrt-windows-storage-streams>=3.2.1; extra == 'winrt'
